.DS_Store
"Icon"
"wolfeutils/Icon"
wolfeutils/__init__.py
wolfeutils/base.py
wolfeutils/cli.py
"wolfeutils/comparative/Icon"
wolfeutils/comparative/__init__.py
"wolfeutils/comparative/panseq/Icon"
wolfeutils/comparative/panseq/__init__.py
wolfeutils/comparative/panseq/labelNewick.py
wolfeutils/comparative/panseq/seqtools.py
"wolfeutils/comparative/pgap/Icon"
wolfeutils/comparative/pgap/__init__.py
wolfeutils/comparative/pgap/workflows.py
wolfeutils/seqmanip/__init__.py
wolfeutils/seqmanip/converters.py
wolfeutils/seqmanip/filters.py
"wolfeutils/tests/Icon"
wolfeutils/tests/__init__.py
"wolfeutils-0.0.2.data/scripts/Icon"
wolfeutils-0.0.2.data/scripts/runPanSeq.sh
wolfeutils-0.0.2.dist-info/DESCRIPTION.rst
"wolfeutils-0.0.2.dist-info/Icon"
wolfeutils-0.0.2.dist-info/METADATA
wolfeutils-0.0.2.dist-info/RECORD
wolfeutils-0.0.2.dist-info/WHEEL
wolfeutils-0.0.2.dist-info/entry_points.txt
wolfeutils-0.0.2.dist-info/metadata.json
wolfeutils-0.0.2.dist-info/pbr.json
wolfeutils-0.0.2.dist-info/top_level.txt
