Metadata-Version: 2.0
Name: wolfeutils
Version: 0.0.2
Summary: Utilities for Wolfe Lab
Home-page: http://github.com/kastman/wolfeutils
Author: Erik Kastman
Author-email: erik.kastman@gmail.com
License: GPL
Platform: UNKNOWN
Classifier: Development Status :: 1 - Planning
Classifier: License :: OSI Approved :: GNU General Public License v3 or later (GPLv3+)
Classifier: Programming Language :: Python
Classifier: Intended Audience :: Science/Research
Classifier: Topic :: Scientific/Engineering :: Bio-Informatics
Requires-Dist: biopython
Requires-Dist: matplotlib
Requires-Dist: matplotlib-venn
Requires-Dist: numpy
Requires-Dist: pandas
Requires-Dist: scipy
Requires-Dist: seaborn
